README.md
setup.py
sleemo/__init__.py
sleemo/framework.py
sleemo/settings.py
sleemo/utils.py
sleemo.egg-info/PKG-INFO
sleemo.egg-info/SOURCES.txt
sleemo.egg-info/dependency_links.txt
sleemo.egg-info/requires.txt
sleemo.egg-info/top_level.txt
sleemo/logging/__init__.py
test/test_framework.py
test/test_logging.py
test/test_utils.py