Metadata-Version: 2.1
Name: sleemo
Version: 0.1.2
Summary: AWS AppSync Direct Lambda Resolver Framework
Home-page: https://github.com/twkiiim/sleemo
Author: Taewoo Kim
Author-email: twkiiim@gmail.com
License: MIT License
Keywords: aws appsync lambda serverless framework
Platform: UNKNOWN
Classifier: Development Status :: 2 - Pre-Alpha
Classifier: License :: OSI Approved :: MIT License
Classifier: Programming Language :: Python
Classifier: Programming Language :: Python :: 3
